jaxrie-19.dist-info/METADATA
jaxrie-19.dist-info/WHEEL
jaxrie/__init__.py
jaxrie/__version__.py
jaxrie/manifold/__init__.py
jaxrie/manifold/_base.py
jaxrie/manifold/_euclidean.py
jaxrie/manifold/_lorentz.py
jaxrie/manifold/_math.py
jaxrie/manifold/_stereographic.py
jaxrie/modules/__init__.py
jaxrie/modules/basic.py
jaxrie/nets/__init__.py
jaxrie/nets/basic.py
jaxrie/optimizers/__init__.py
jaxrie/optimizers/alias.py
jaxrie/optimizers/transform.py
jaxrie/optimizers/updates.py
jaxrie/py.typed
jaxrie-19.dist-info/RECORD
