Metadata-Version: 2.1
Name: jaxrie
Version: 19
Summary: Riemannian JAX
Author-Email: Nasy <nasyxx+git@gmail.com>
License: MIT
Requires-Python: >=3.10
Requires-Dist: jax>=0.4.6
Requires-Dist: jaxlib>=0.4.6
Requires-Dist: dm-haiku>=0.0.9
Requires-Dist: optax
